OireachtasAPI/__init__.py
OireachtasAPI/api.py
OireachtasAPI/errors.py
OireachtasAPI/urls.py
OireachtasAPI/wrapper.py
oireachtasapiwrapper-1.0.1.dist-info/licenses/LICENSE.txt
oireachtasapiwrapper-1.0.1.dist-info/METADATA
oireachtasapiwrapper-1.0.1.dist-info/WHEEL
oireachtasapiwrapper-1.0.1.dist-info/top_level.txt
oireachtasapiwrapper-1.0.1.dist-info/RECORD
