Metadata-Version: 2.4
Name: OireachtasAPIWrapper
Version: 1.0.1
Summary: Python wrapper client for the Oireachtas public API
Home-page: https://github.com/aaronbowman/OireachtasAPIWrapper
Author: Aaron Bowman
Author-email: Aaron Bowman <aaronrbowman12@gmail.com>
License: MIT License
Project-URL: Homepage, https://github.com/aaronbowman/OireachtasAPIWrapper
Project-URL: Repository, https://github.com/aaronbowman/OireachtasAPIWrapper
Project-URL: Documentation, https://github.com/aaronbowman/OireachtasAPIWrapper#readme
Project-URL: Issues, https://github.com/aaronbowman/OireachtasAPIWrapper/issues
Classifier: Programming Language :: Python
Classifier: Programming Language :: Python :: 3
Classifier: License :: OSI Approved :: MIT License
Classifier: Operating System :: OS Independent
Requires-Python: >=3.9
License-File: LICENSE.txt
Requires-Dist: requests>=2.31
Provides-Extra: test
Requires-Dist: pytest>=8.2.0; extra == "test"
Requires-Dist: httpx>=0.27; extra == "test"
Provides-Extra: build
Requires-Dist: build>=1.2.1; extra == "build"
Dynamic: author
Dynamic: home-page
Dynamic: license-file
